khmer_text_transliteration/__init__.py
khmer_text_transliteration/config.py
khmer_text_transliteration/data_processing.py
khmer_text_transliteration/evaluate.py
khmer_text_transliteration/model.py
khmer_text_transliteration/predict.py
khmer_text_transliteration/predict_with_clean.py
khmer_text_transliteration/train.py
khmer_text_transliteration/data/processed/khmer_transliteration_assets.pkl
khmer_text_transliteration/data/processed/khmer_transliteration_assets_old.pkl
khmer_text_transliteration/data/raw/.DS_Store
khmer_text_transliteration/data/raw/eng_khm_data.txt
khmer_text_transliteration/data/raw/khmer_words.txt
khmer_text_transliteration/models/.DS_Store
khmer_text_transliteration/models/pretrained/.DS_Store
khmer_text_transliteration/models/pretrained/khmer_transliterator.keras
khmer_text_transliteration/models/pretrained/khmer_transliterator_old.keras
khmer_english_transliteration-0.1.4.dist-info/LICENSE
khmer_english_transliteration-0.1.4.dist-info/METADATA
khmer_english_transliteration-0.1.4.dist-info/WHEEL
khmer_english_transliteration-0.1.4.dist-info/top_level.txt
khmer_english_transliteration-0.1.4.dist-info/RECORD
