Metadata-Version: 2.1
Name: khmer-english-transliteration
Version: 0.1.4
Summary: A Python package for transliterating English text to Khmer script.
Home-page: https://github.com/Chhunneng/khmer-text-transliteration
Author: Chanchhunneng Chrea
Author-email: chreachanchhunneng@gmail.com
Classifier: Programming Language :: Python :: 3
Classifier: License :: OSI Approved :: MIT License
Classifier: Operating System :: OS Independent
Requires-Python: >=3.6
License-File: LICENSE
Requires-Dist: tensorflow>=2.0
Requires-Dist: numpy
Requires-Dist: scikit-learn
Requires-Dist: python-Levenshtein
Requires-Dist: rapidfuzz
Requires-Dist: gradio
